musamusa/main.py
musamusa-0.0.0.dist-info/LICENSE
musamusa-0.0.0.dist-info/WHEEL
musamusa-0.0.0.dist-info/METADATA
musamusa-0.0.0.dist-info/RECORD
