Metadata-Version: 2.1
Name: musamusa
Version: 0.0.0
Summary: Tool to display annotated texts.
License: GPLv3
Author: suizokukan
Author-email: suizokukan@orange.fr
Requires-Python: >=3.9,<4.0
Classifier: License :: Other/Proprietary License
Classifier: Programming Language :: Python :: 3
Classifier: Programming Language :: Python :: 3.9
Requires-Dist: rich (>=9.11.1,<10.0.0)
